bankstatementextractor/BanksExtractor.py
bankstatementextractor/Incom_expense.py
bankstatementextractor/__init__.py
bankstatementextractor/banks.py
bankstatementextractor/banks_utils.py
bankstatementextractor/constants.py
bankstatementextractor/global_percentiles.json
bankstatementextractor/keywords.csv
bankstatementextractor/test.py
bankstatementextractor/throw_away.csv
bankstatementextractor/models/.DS_Store
bankstatementextractor/models/best.pt
bankstatementextractor/models/categories.csv
bankstatementextractor/models/lean/.DS_Store
bankstatementextractor/models/lean/labels
bankstatementextractor/models/lean/0.9384675110399379/.DS_Store
bankstatementextractor/models/lean/0.9384675110399379/keras_metadata.pb
bankstatementextractor/models/lean/0.9384675110399379/saved_model.pb
bankstatementextractor/models/lean/0.9384675110399379/variables/variables.data-00000-of-00001
bankstatementextractor/models/lean/0.9384675110399379/variables/variables.index
bankstatementextractor/models/places/.DS_Store
bankstatementextractor/models/places/categories.csv
bankstatementextractor/models/places/0.706/.DS_Store
bankstatementextractor/models/places/0.706/keras_metadata.pb
bankstatementextractor/models/places/0.706/saved_model.pb
bankstatementextractor/models/places/0.706/variables/variables.data-00000-of-00001
bankstatementextractor/models/places/0.706/variables/variables.index
bankstatementextractor/models/places/0.726/.DS_Store
bankstatementextractor/models/places/0.726/keras_metadata.pb
bankstatementextractor/models/places/0.726/saved_model.pb
bankstatementextractor/models/places/0.726/variables/variables.data-00000-of-00001
bankstatementextractor/models/places/0.726/variables/variables.index
bankstatementextractor/models/words/.DS_Store
bankstatementextractor/models/words/0.708/.DS_Store
bankstatementextractor/models/words/0.708/keras_metadata.pb
bankstatementextractor/models/words/0.708/saved_model.pb
banktest-1.1.1.dist-info/LICENSE
banktest-1.1.1.dist-info/METADATA
banktest-1.1.1.dist-info/WHEEL
banktest-1.1.1.dist-info/top_level.txt
banktest-1.1.1.dist-info/RECORD
